README.md
setup.cfg
setup.py
ProjZ.py.egg-info/PKG-INFO
ProjZ.py.egg-info/SOURCES.txt
ProjZ.py.egg-info/dependency_links.txt
ProjZ.py.egg-info/requires.txt
ProjZ.py.egg-info/top_level.txt
projz/__init__.py
projz/__main__.py
projz/client.py
projz/api/__init__.py
projz/api/request_manager.py
projz/api/control/__init__.py
projz/api/control/rpc.py
projz/api/headers/__init__.py
projz/api/headers/abc_headers_provider.py
projz/api/headers/headers_provider.py
projz/api/util/__init__.py
projz/api/util/copy_to_buffer_writer.py
projz/enum/__init__.py
projz/enum/auth_purpose.py
projz/enum/auth_type.py
projz/enum/chat_message_type.py
projz/enum/chat_query_type.py
projz/enum/chat_thread_type.py
projz/enum/circle_filter_type.py
projz/enum/circle_members_query_type.py
projz/enum/comment_type.py
projz/enum/content_region.py
projz/enum/currency_type.py
projz/enum/gender.py
projz/enum/object_type.py
projz/enum/party_query_type.py
projz/enum/upload_target.py
projz/enum/user_task_type.py
projz/enum/ws_event_type.py
projz/error/__init__.py
projz/error/classes.py
projz/model/__init__.py
projz/model/account.py
projz/model/blocked_item_wrapper.py
projz/model/blog.py
projz/model/category.py
projz/model/chat.py
projz/model/chat_message.py
projz/model/circle.py
projz/model/comment.py
projz/model/currency.py
projz/model/default_background_media.py
projz/model/dice.py
projz/model/gift_box.py
projz/model/link_info.py
projz/model/media.py
projz/model/member_title.py
projz/model/party.py
projz/model/poll.py
projz/model/qi_vote_full_info.py
projz/model/qi_vote_info.py
projz/model/reaction.py
projz/model/rich_format.py
projz/model/sticker.py
projz/model/transfer_order.py
projz/model/user.py
projz/model/user_task.py
projz/model/wallet.py
projz/model/parse/__init__.py
projz/model/parse/parseutils.py
projz/model/response/__init__.py
projz/model/response/auth_result.py
projz/model/response/block_users_info.py
projz/model/response/member_titles_info.py
projz/model/response/multi_invitation_code_info.py
projz/model/util/__init__.py
projz/model/util/paginated_list.py
projz/model/util/rich_format_builder.py
projz/model/util/rich_format_text_builder.py
