Metadata-Version: 2.1
Name: ProjZ.py
Version: 2.4.6
Summary: An asynchronous library for creating scripts and chatbots in Project Z.
Home-page: https://github.com/D4rkwat3r/ProjZ
Author: D4rkwat3r
Author-email: ktoya170214@gmail.com
License: UNKNOWN
Keywords: project-z,projectz,projz,bots,api,supersymlab,projz-bot,projz-bots,projz-api
Platform: UNKNOWN
Requires-Python: >=3.7
